tartaruga/__init__.py
tartaruga/tartaruga.lua
tartaruga/tartaruga.py
tartaruga-0.0.5.dist-info/METADATA
tartaruga-0.0.5.dist-info/WHEEL
tartaruga-0.0.5.dist-info/top_level.txt
tartaruga-0.0.5.dist-info/RECORD
