Metadata-Version: 2.1
Name: tartaruga
Version: 0.0.5
Summary: tartaruga ratelimiter
Home-page: UNKNOWN
Author: Devmons s.r.o.
License: GPL3
Platform: UNKNOWN
Requires-Dist: redis (>=3.3.11)
